{"BasicSettingController":{"Data":{"ProgramToRun":"D:\\school\\oop\\4\\Lab 4\\E2\\Debug\\E2.exe","OptionalWorkingDirectory":"D:\\school\\oop\\4\\Lab 4\\E2\\E2\\","Arguments":"","CompileBeforeRunning":true,"OptimizedBuild":false},"IsSelectedByProjectPath":{"E2\\E2.vcxproj":true}},"FilterSettingController":{"AdditionalSourcePatterns":[],"AdditionalModulePatterns":[],"ExcludedSourcePatterns":[],"ExcludedModulePatterns":[],"UnifiedDiffs":[]},"ImportExportSettingController":{"Exports":[],"InputCoverages":[],"CoverChildrenProcesses":false,"AggregateByFile":true},"MiscellaneousSettingController":{"OptionalConfigFile":null,"LogTypeValue":0,"ContinueAfterCppExceptions":false}}